function_shield/__init__.py
function_shield/lib/libfunctionshieldcore.so
function_shield-1.2.7.dist-info/METADATA
function_shield-1.2.7.dist-info/WHEEL
function_shield-1.2.7.dist-info/top_level.txt
function_shield-1.2.7.dist-info/zip-safe
function_shield-1.2.7.dist-info/RECORD
