Metadata-Version: 2.1
Name: function-shield
Version: 1.2.7
Summary: UNKNOWN
Home-page: UNKNOWN
Author: PureSec
Author-email: support@puresec.io
License: UNKNOWN
Platform: UNKNOWN
